{
  "behavior": {
    "minecraft:block": {
      "block": "minecraft:light_gray_carpet"
    },
    "minecraft:dispensable": {
      "behavior": "minecraft:equip_entity"
    },
    "minecraft:equipment": {
      "allowed_entities": [
        "minecraft:llama",
        "minecraft:trader_llama"
      ],
      "equip_sound": "minecraft:entity.llama.swag",
      "model": "minecraft:light_gray_carpet",
      "slot": "body",
      "swappable": true
    },
    "minecraft:fuel": {
      "ticks": 67
    },
    "minecraft:stackable": 64
  },
  "display": {
    "model": "minecraft:light_gray_carpet",
    "translation_key": "block.minecraft.light_gray_carpet"
  }
}